meerschaum/__init__.py
meerschaum/__main__.py
meerschaum/_internal/__init__.py
meerschaum/_internal/entry.py
meerschaum/_internal/static.py
meerschaum/_internal/arguments/__init__.py
meerschaum/_internal/arguments/_parse_arguments.py
meerschaum/_internal/arguments/_parser.py
meerschaum/_internal/cli/__init__.py
meerschaum/_internal/cli/daemons.py
meerschaum/_internal/cli/entry.py
meerschaum/_internal/cli/workers.py
meerschaum/_internal/docs/__init__.py
meerschaum/_internal/docs/index.py
meerschaum/_internal/shell/Shell.py
meerschaum/_internal/shell/ShellCompleter.py
meerschaum/_internal/shell/ValidAutoSuggest.py
meerschaum/_internal/shell/__init__.py
meerschaum/_internal/shell/updates.py
meerschaum/_internal/shell/resources/__init__.py
meerschaum/_internal/term/TermPageHandler.py
meerschaum/_internal/term/__init__.py
meerschaum/_internal/term/tools.py
meerschaum/actions/__init__.py
meerschaum/actions/api.py
meerschaum/actions/attach.py
meerschaum/actions/bootstrap.py
meerschaum/actions/clear.py
meerschaum/actions/copy.py
meerschaum/actions/deduplicate.py
meerschaum/actions/delete.py
meerschaum/actions/drop.py
meerschaum/actions/edit.py
meerschaum/actions/index.py
meerschaum/actions/install.py
meerschaum/actions/login.py
meerschaum/actions/os.py
meerschaum/actions/pause.py
meerschaum/actions/python.py
meerschaum/actions/register.py
meerschaum/actions/reload.py
meerschaum/actions/restart.py
meerschaum/actions/setup.py
meerschaum/actions/sh.py
meerschaum/actions/show.py
meerschaum/actions/sql.py
meerschaum/actions/stack.py
meerschaum/actions/start.py
meerschaum/actions/stop.py
meerschaum/actions/sync.py
meerschaum/actions/tag.py
meerschaum/actions/uninstall.py
meerschaum/actions/upgrade.py
meerschaum/actions/verify.py
meerschaum/api/__init__.py
meerschaum/api/_chain.py
meerschaum/api/_chunks.py
meerschaum/api/_events.py
meerschaum/api/_exceptions.py
meerschaum/api/_oauth2.py
meerschaum/api/_tokens.py
meerschaum/api/_websockets.py
meerschaum/api/dash/__init__.py
meerschaum-3.1.4.dist-info/licenses/LICENSE
meerschaum-3.1.4.dist-info/licenses/NOTICE
meerschaum-3.1.4.dist-info/METADATA
meerschaum-3.1.4.dist-info/WHEEL
meerschaum-3.1.4.dist-info/entry_points.txt
meerschaum-3.1.4.dist-info/top_level.txt
meerschaum-3.1.4.dist-info/zip-safe
meerschaum-3.1.4.dist-info/RECORD
