Metadata-Version: 2.4
Name: meerschaum
Version: 3.1.4
Summary: Sync Time-Series Pipes with Meerschaum
Author-email: Bennett Meares <bennett.meares@gmail.com>
Maintainer-email: Bennett Meares <bennett.meares@gmail.com>
License-Expression: Apache-2.0
Project-URL: Documentation, https://docs.meerschaum.io
Project-URL: Changelog, https://meerschaum.io/news/changelog
Project-URL: GitHub, https://github.com/bmeares/Meerschaum
Project-URL: Homepage, https://meerschaum.io
Project-URL: Donate, https://github.com/sponsors/bmeares
Project-URL: Discord, https://discord.gg/8U8qMUjvcc
Classifier: Development Status :: 5 - Production/Stable
Classifier: Intended Audience :: System Administrators
Classifier: Operating System :: POSIX :: Linux
Classifier: Operating System :: Microsoft :: Windows
Classifier: Operating System :: MacOS
Classifier: Programming Language :: SQL
Classifier: Programming Language :: Python :: 3.9
Classifier: Programming Language :: Python :: 3.10
Classifier: Programming Language :: Python :: 3.11
Classifier: Programming Language :: Python :: 3.12
Classifier: Programming Language :: Python :: 3.13
Classifier: Programming Language :: Python :: 3.14
Classifier: Topic :: Database
Classifier: Natural Language :: English
Requires-Python: >=3.8
License-File: LICENSE
License-File: NOTICE
Provides-Extra: required
Provides-Extra: minimal
Provides-Extra: formatting
Requires-Dist: pprintpp>=0.4.0; extra == "formatting"
Requires-Dist: asciitree>=0.3.3; extra == "formatting"
Requires-Dist: typing-extensions>=4.7.1; extra == "formatting"
Requires-Dist: pygments>=2.7.2; extra == "formatting"
Requires-Dist: colorama>=0.4.3; extra == "formatting"
Requires-Dist: rich>=13.4.2; extra == "formatting"
Requires-Dist: more-termcolor>=1.1.3; extra == "formatting"
Requires-Dist: humanfriendly>=10.0.0; extra == "formatting"
Provides-Extra: core
Requires-Dist: wheel>=0.34.2; extra == "core"
Requires-Dist: setuptools>=63.3.0; extra == "core"
Requires-Dist: PyYAML>=5.3.1; extra == "core"
Requires-Dist: pip>=22.0.4; extra == "core"
Requires-Dist: update-checker>=0.18.0; extra == "core"
Requires-Dist: semver>=3.0.2; extra == "core"
Requires-Dist: pathspec>=0.9.0; extra == "core"
Requires-Dist: python-dateutil>=2.7.5; extra == "core"
Requires-Dist: requests>=2.32.3; extra == "core"
Requires-Dist: certifi>=2024.8.30; extra == "core"
Requires-Dist: idna>=3.10.0; extra == "core"
Requires-Dist: binaryornot>=0.4.4; extra == "core"
Requires-Dist: pyvim>=3.0.2; extra == "core"
Requires-Dist: ptpython>=3.0.27; extra == "core"
Requires-Dist: aiofiles>=0.6.0; extra == "core"
Requires-Dist: packaging>=21.3.0; extra == "core"
Requires-Dist: prompt-toolkit>=3.0.39; extra == "core"
Requires-Dist: more-itertools>=8.7.0; extra == "core"
Requires-Dist: fasteners>=0.19.0; extra == "core"
Requires-Dist: virtualenv>=20.1.0; extra == "core"
Requires-Dist: attrs>=24.2.0; extra == "core"
Requires-Dist: uv>=0.2.11; extra == "core"
Requires-Dist: pydantic>=2.11.7; extra == "core"
Requires-Dist: annotated-types>=0.7.0; extra == "core"
Provides-Extra: jobs
Requires-Dist: dill>=0.4.0; extra == "jobs"
Requires-Dist: python-daemon>=3.1.2; extra == "jobs"
Requires-Dist: watchfiles>=1.1.0; extra == "jobs"
Requires-Dist: psutil>=7.0.0; extra == "jobs"
Provides-Extra: drivers
Requires-Dist: cryptography>=38.0.1; extra == "drivers"
Requires-Dist: psycopg[binary]>=3.2.9; extra == "drivers"
Requires-Dist: psycopg2-binary>=2.9.11; extra == "drivers"
Requires-Dist: PyMySQL>=0.9.0; extra == "drivers"
Requires-Dist: aiomysql>=0.0.21; extra == "drivers"
Requires-Dist: sqlalchemy-cockroachdb>=2.0.0; extra == "drivers"
Requires-Dist: duckdb>=1.0.0; extra == "drivers"
Requires-Dist: duckdb-engine>=0.13.0; extra == "drivers"
Provides-Extra: drivers-extras
Requires-Dist: pyodbc>=4.0.30; extra == "drivers-extras"
Requires-Dist: oracledb>=2.5.0; extra == "drivers-extras"
Provides-Extra: cli
Requires-Dist: pgcli>=3.1.0; extra == "cli"
Requires-Dist: mycli>=1.23.2; extra == "cli"
Requires-Dist: litecli>=1.5.0; extra == "cli"
Requires-Dist: mssql-cli>=1.0.0; extra == "cli"
Requires-Dist: gadwall>=0.2.0; extra == "cli"
Provides-Extra: gis
Requires-Dist: pyproj>=3.7.1; extra == "gis"
Requires-Dist: geopandas>=1.0.1; extra == "gis"
Requires-Dist: shapely>=2.0.7; extra == "gis"
Provides-Extra: stack
Requires-Dist: docker-compose>=1.29.2; extra == "stack"
Provides-Extra: build
Requires-Dist: cx_Freeze>=7.0.0; extra == "build"
Requires-Dist: pyinstaller>6.6.0; extra == "build"
Provides-Extra: dev-tools
Requires-Dist: twine>=3.2.0; extra == "dev-tools"
Requires-Dist: tuna>=0.5.3; extra == "dev-tools"
Requires-Dist: snakeviz>=2.1.0; extra == "dev-tools"
Requires-Dist: mypy>=0.812.0; extra == "dev-tools"
Requires-Dist: pytest>=6.2.2; extra == "dev-tools"
Requires-Dist: pytest-xdist>=3.2.1; extra == "dev-tools"
Requires-Dist: heartrate>=0.2.1; extra == "dev-tools"
Requires-Dist: build>=1.2.1; extra == "dev-tools"
Requires-Dist: attrs>=24.2.0; extra == "dev-tools"
Provides-Extra: setup
Provides-Extra: docs
Requires-Dist: mkdocs>=1.1.2; extra == "docs"
Requires-Dist: mkdocs-material>=6.2.5; extra == "docs"
Requires-Dist: mkdocs-material-extensions>=1.0.3; extra == "docs"
Requires-Dist: mkdocs-autolinks-plugin>=0.2.0; extra == "docs"
Requires-Dist: mkdocs-awesome-pages-plugin>=2.5.0; extra == "docs"
Requires-Dist: mkdocs-section-index>=0.3.3; extra == "docs"
Requires-Dist: mkdocs-linkcheck>=1.0.6; extra == "docs"
Requires-Dist: mkdocs-redirects>=1.0.4; extra == "docs"
Requires-Dist: jinja2>=3.1.6; extra == "docs"
Provides-Extra: gui
Requires-Dist: pywebview>=3.6.3; extra == "gui"
Requires-Dist: pycparser>=2.21.0; extra == "gui"
Provides-Extra: extras
Requires-Dist: cmd2>=1.4.0; extra == "extras"
Requires-Dist: ruamel.yaml>=0.16.12; extra == "extras"
Requires-Dist: modin[ray]>=0.8.3; extra == "extras"
Requires-Dist: nanoid>=2.0.0; extra == "extras"
Requires-Dist: importlib-metadata>=4.12.0; extra == "extras"
Provides-Extra: sql
Requires-Dist: numpy>=2.3.1; extra == "sql"
Requires-Dist: pandas[parquet]>=2.3.1; extra == "sql"
Requires-Dist: pyarrow>=20.0.0; extra == "sql"
Requires-Dist: dask[complete]>=2024.12.1; extra == "sql"
Requires-Dist: partd>=1.4.2; extra == "sql"
Requires-Dist: pytz; extra == "sql"
Requires-Dist: joblib>=1.5.1; extra == "sql"
Requires-Dist: SQLAlchemy>=2.0.41; extra == "sql"
Requires-Dist: GeoAlchemy2>=0.18.0; extra == "sql"
Requires-Dist: databases>=0.9.0; extra == "sql"
Requires-Dist: aiosqlite>=0.21.0; extra == "sql"
Requires-Dist: asyncpg>=0.30.0; extra == "sql"
Requires-Dist: cryptography>=38.0.1; extra == "sql"
Requires-Dist: psycopg[binary]>=3.2.9; extra == "sql"
Requires-Dist: psycopg2-binary>=2.9.11; extra == "sql"
Requires-Dist: PyMySQL>=0.9.0; extra == "sql"
Requires-Dist: aiomysql>=0.0.21; extra == "sql"
Requires-Dist: sqlalchemy-cockroachdb>=2.0.0; extra == "sql"
Requires-Dist: duckdb>=1.0.0; extra == "sql"
Requires-Dist: duckdb-engine>=0.13.0; extra == "sql"
Requires-Dist: wheel>=0.34.2; extra == "sql"
Requires-Dist: setuptools>=63.3.0; extra == "sql"
Requires-Dist: PyYAML>=5.3.1; extra == "sql"
Requires-Dist: pip>=22.0.4; extra == "sql"
Requires-Dist: update-checker>=0.18.0; extra == "sql"
Requires-Dist: semver>=3.0.2; extra == "sql"
Requires-Dist: pathspec>=0.9.0; extra == "sql"
Requires-Dist: python-dateutil>=2.7.5; extra == "sql"
Requires-Dist: requests>=2.32.3; extra == "sql"
Requires-Dist: certifi>=2024.8.30; extra == "sql"
Requires-Dist: idna>=3.10.0; extra == "sql"
Requires-Dist: binaryornot>=0.4.4; extra == "sql"
Requires-Dist: pyvim>=3.0.2; extra == "sql"
Requires-Dist: ptpython>=3.0.27; extra == "sql"
Requires-Dist: aiofiles>=0.6.0; extra == "sql"
Requires-Dist: packaging>=21.3.0; extra == "sql"
Requires-Dist: prompt-toolkit>=3.0.39; extra == "sql"
Requires-Dist: more-itertools>=8.7.0; extra == "sql"
Requires-Dist: fasteners>=0.19.0; extra == "sql"
Requires-Dist: virtualenv>=20.1.0; extra == "sql"
Requires-Dist: attrs>=24.2.0; extra == "sql"
Requires-Dist: uv>=0.2.11; extra == "sql"
Requires-Dist: pydantic>=2.11.7; extra == "sql"
Requires-Dist: annotated-types>=0.7.0; extra == "sql"
Requires-Dist: pyproj>=3.7.1; extra == "sql"
Requires-Dist: geopandas>=1.0.1; extra == "sql"
Requires-Dist: shapely>=2.0.7; extra == "sql"
Provides-Extra: dash
Requires-Dist: Flask-Compress>=1.17.0; extra == "dash"
Requires-Dist: dash>=3.1.1; extra == "dash"
Requires-Dist: dash-bootstrap-components>=1.7.1; extra == "dash"
Requires-Dist: dash-ace>=0.2.1; extra == "dash"
Requires-Dist: dash-extensions>=2.0.4; extra == "dash"
Requires-Dist: dash-daq>=0.6.0; extra == "dash"
Requires-Dist: terminado>=0.18.1; extra == "dash"
Requires-Dist: tornado>=6.5.1; extra == "dash"
Provides-Extra: api
Requires-Dist: uvicorn[standard]>=0.35.0; extra == "api"
Requires-Dist: gunicorn>=23.0.0; extra == "api"
Requires-Dist: python-dotenv>=1.1.1; extra == "api"
Requires-Dist: websockets>=15.0.1; extra == "api"
Requires-Dist: fastapi>=0.116.0; extra == "api"
Requires-Dist: fastapi-login>=1.10.3; extra == "api"
Requires-Dist: python-multipart>=0.0.20; extra == "api"
Requires-Dist: httpx>=0.28.1; extra == "api"
Requires-Dist: httpcore>=1.0.9; extra == "api"
Requires-Dist: valkey>=6.1.0; extra == "api"
Requires-Dist: python-jose>=3.5.0; extra == "api"
Requires-Dist: numpy>=2.3.1; extra == "api"
Requires-Dist: pandas[parquet]>=2.3.1; extra == "api"
Requires-Dist: pyarrow>=20.0.0; extra == "api"
Requires-Dist: dask[complete]>=2024.12.1; extra == "api"
Requires-Dist: partd>=1.4.2; extra == "api"
Requires-Dist: pytz; extra == "api"
Requires-Dist: joblib>=1.5.1; extra == "api"
Requires-Dist: SQLAlchemy>=2.0.41; extra == "api"
Requires-Dist: GeoAlchemy2>=0.18.0; extra == "api"
Requires-Dist: databases>=0.9.0; extra == "api"
Requires-Dist: aiosqlite>=0.21.0; extra == "api"
Requires-Dist: asyncpg>=0.30.0; extra == "api"
Requires-Dist: cryptography>=38.0.1; extra == "api"
Requires-Dist: psycopg[binary]>=3.2.9; extra == "api"
Requires-Dist: psycopg2-binary>=2.9.11; extra == "api"
Requires-Dist: PyMySQL>=0.9.0; extra == "api"
Requires-Dist: aiomysql>=0.0.21; extra == "api"
Requires-Dist: sqlalchemy-cockroachdb>=2.0.0; extra == "api"
Requires-Dist: duckdb>=1.0.0; extra == "api"
Requires-Dist: duckdb-engine>=0.13.0; extra == "api"
Requires-Dist: wheel>=0.34.2; extra == "api"
Requires-Dist: setuptools>=63.3.0; extra == "api"
Requires-Dist: PyYAML>=5.3.1; extra == "api"
Requires-Dist: pip>=22.0.4; extra == "api"
Requires-Dist: update-checker>=0.18.0; extra == "api"
Requires-Dist: semver>=3.0.2; extra == "api"
Requires-Dist: pathspec>=0.9.0; extra == "api"
Requires-Dist: python-dateutil>=2.7.5; extra == "api"
Requires-Dist: requests>=2.32.3; extra == "api"
Requires-Dist: certifi>=2024.8.30; extra == "api"
Requires-Dist: idna>=3.10.0; extra == "api"
Requires-Dist: binaryornot>=0.4.4; extra == "api"
Requires-Dist: pyvim>=3.0.2; extra == "api"
Requires-Dist: ptpython>=3.0.27; extra == "api"
Requires-Dist: aiofiles>=0.6.0; extra == "api"
Requires-Dist: packaging>=21.3.0; extra == "api"
Requires-Dist: prompt-toolkit>=3.0.39; extra == "api"
Requires-Dist: more-itertools>=8.7.0; extra == "api"
Requires-Dist: fasteners>=0.19.0; extra == "api"
Requires-Dist: virtualenv>=20.1.0; extra == "api"
Requires-Dist: attrs>=24.2.0; extra == "api"
Requires-Dist: uv>=0.2.11; extra == "api"
Requires-Dist: pydantic>=2.11.7; extra == "api"
Requires-Dist: annotated-types>=0.7.0; extra == "api"
Requires-Dist: pyproj>=3.7.1; extra == "api"
Requires-Dist: geopandas>=1.0.1; extra == "api"
Requires-Dist: shapely>=2.0.7; extra == "api"
Requires-Dist: pprintpp>=0.4.0; extra == "api"
Requires-Dist: asciitree>=0.3.3; extra == "api"
Requires-Dist: typing-extensions>=4.7.1; extra == "api"
Requires-Dist: pygments>=2.7.2; extra == "api"
Requires-Dist: colorama>=0.4.3; extra == "api"
Requires-Dist: rich>=13.4.2; extra == "api"
Requires-Dist: more-termcolor>=1.1.3; extra == "api"
Requires-Dist: humanfriendly>=10.0.0; extra == "api"
Requires-Dist: Flask-Compress>=1.17.0; extra == "api"
Requires-Dist: dash>=3.1.1; extra == "api"
Requires-Dist: dash-bootstrap-components>=1.7.1; extra == "api"
Requires-Dist: dash-ace>=0.2.1; extra == "api"
Requires-Dist: dash-extensions>=2.0.4; extra == "api"
Requires-Dist: dash-daq>=0.6.0; extra == "api"
Requires-Dist: terminado>=0.18.1; extra == "api"
Requires-Dist: tornado>=6.5.1; extra == "api"
Requires-Dist: dill>=0.4.0; extra == "api"
Requires-Dist: python-daemon>=3.1.2; extra == "api"
Requires-Dist: watchfiles>=1.1.0; extra == "api"
Requires-Dist: psutil>=7.0.0; extra == "api"
Provides-Extra: full
Requires-Dist: pprintpp>=0.4.0; extra == "full"
Requires-Dist: asciitree>=0.3.3; extra == "full"
Requires-Dist: typing-extensions>=4.7.1; extra == "full"
Requires-Dist: pygments>=2.7.2; extra == "full"
Requires-Dist: colorama>=0.4.3; extra == "full"
Requires-Dist: rich>=13.4.2; extra == "full"
Requires-Dist: more-termcolor>=1.1.3; extra == "full"
Requires-Dist: humanfriendly>=10.0.0; extra == "full"
Requires-Dist: wheel>=0.34.2; extra == "full"
Requires-Dist: setuptools>=63.3.0; extra == "full"
Requires-Dist: PyYAML>=5.3.1; extra == "full"
Requires-Dist: pip>=22.0.4; extra == "full"
Requires-Dist: update-checker>=0.18.0; extra == "full"
Requires-Dist: semver>=3.0.2; extra == "full"
Requires-Dist: pathspec>=0.9.0; extra == "full"
Requires-Dist: python-dateutil>=2.7.5; extra == "full"
Requires-Dist: requests>=2.32.3; extra == "full"
Requires-Dist: certifi>=2024.8.30; extra == "full"
Requires-Dist: idna>=3.10.0; extra == "full"
Requires-Dist: binaryornot>=0.4.4; extra == "full"
Requires-Dist: pyvim>=3.0.2; extra == "full"
Requires-Dist: ptpython>=3.0.27; extra == "full"
Requires-Dist: aiofiles>=0.6.0; extra == "full"
Requires-Dist: packaging>=21.3.0; extra == "full"
Requires-Dist: prompt-toolkit>=3.0.39; extra == "full"
Requires-Dist: more-itertools>=8.7.0; extra == "full"
Requires-Dist: fasteners>=0.19.0; extra == "full"
Requires-Dist: virtualenv>=20.1.0; extra == "full"
Requires-Dist: attrs>=24.2.0; extra == "full"
Requires-Dist: uv>=0.2.11; extra == "full"
Requires-Dist: pydantic>=2.11.7; extra == "full"
Requires-Dist: annotated-types>=0.7.0; extra == "full"
Requires-Dist: dill>=0.4.0; extra == "full"
Requires-Dist: python-daemon>=3.1.2; extra == "full"
Requires-Dist: watchfiles>=1.1.0; extra == "full"
Requires-Dist: psutil>=7.0.0; extra == "full"
Requires-Dist: cryptography>=38.0.1; extra == "full"
Requires-Dist: psycopg[binary]>=3.2.9; extra == "full"
Requires-Dist: psycopg2-binary>=2.9.11; extra == "full"
Requires-Dist: PyMySQL>=0.9.0; extra == "full"
Requires-Dist: aiomysql>=0.0.21; extra == "full"
Requires-Dist: sqlalchemy-cockroachdb>=2.0.0; extra == "full"
Requires-Dist: duckdb>=1.0.0; extra == "full"
Requires-Dist: duckdb-engine>=0.13.0; extra == "full"
Requires-Dist: pyproj>=3.7.1; extra == "full"
Requires-Dist: geopandas>=1.0.1; extra == "full"
Requires-Dist: shapely>=2.0.7; extra == "full"
Requires-Dist: pywebview>=3.6.3; extra == "full"
Requires-Dist: pycparser>=2.21.0; extra == "full"
Requires-Dist: numpy>=2.3.1; extra == "full"
Requires-Dist: pandas[parquet]>=2.3.1; extra == "full"
Requires-Dist: pyarrow>=20.0.0; extra == "full"
Requires-Dist: dask[complete]>=2024.12.1; extra == "full"
Requires-Dist: partd>=1.4.2; extra == "full"
Requires-Dist: pytz; extra == "full"
Requires-Dist: joblib>=1.5.1; extra == "full"
Requires-Dist: SQLAlchemy>=2.0.41; extra == "full"
Requires-Dist: GeoAlchemy2>=0.18.0; extra == "full"
Requires-Dist: databases>=0.9.0; extra == "full"
Requires-Dist: aiosqlite>=0.21.0; extra == "full"
Requires-Dist: asyncpg>=0.30.0; extra == "full"
Requires-Dist: Flask-Compress>=1.17.0; extra == "full"
Requires-Dist: dash>=3.1.1; extra == "full"
Requires-Dist: dash-bootstrap-components>=1.7.1; extra == "full"
Requires-Dist: dash-ace>=0.2.1; extra == "full"
Requires-Dist: dash-extensions>=2.0.4; extra == "full"
Requires-Dist: dash-daq>=0.6.0; extra == "full"
Requires-Dist: terminado>=0.18.1; extra == "full"
Requires-Dist: tornado>=6.5.1; extra == "full"
Requires-Dist: uvicorn[standard]>=0.35.0; extra == "full"
Requires-Dist: gunicorn>=23.0.0; extra == "full"
Requires-Dist: python-dotenv>=1.1.1; extra == "full"
Requires-Dist: websockets>=15.0.1; extra == "full"
Requires-Dist: fastapi>=0.116.0; extra == "full"
Requires-Dist: fastapi-login>=1.10.3; extra == "full"
Requires-Dist: python-multipart>=0.0.20; extra == "full"
Requires-Dist: httpx>=0.28.1; extra == "full"
Requires-Dist: httpcore>=1.0.9; extra == "full"
Requires-Dist: valkey>=6.1.0; extra == "full"
Requires-Dist: python-jose>=3.5.0; extra == "full"
Dynamic: license-file
Dynamic: provides-extra
